{
    "kind": "List",
    "apiVersion": "v1",
    "items": [
        {
            "kind": "ImageStream",
            "apiVersion": "image.openshift.io/v1",
            "metadata": {
                "name": "s2i-mmgaggle-minimal-notebook",
                "labels": {
                    "build": "s2i-mmgaggle-minimal-notebook"
                }
            },
            "spec": {
                "lookupPolicy": {
                    "local": true
                }
            }
        },
        {
            "kind": "BuildConfig",
            "apiVersion": "build.openshift.io/v1",
            "metadata": {
                "name": "s2i-mmgaggle-minimal-notebook-py36",
                "labels": {
                    "build": "s2i-mmgaggle-minimal-notebook"
                }
            },
            "spec": {
                "triggers": [
                    {
                        "type": "ConfigChange"
                    },
                    {
                        "type": "ImageChange"
                    }
                ],
                "source": {
                    "type": "Git",
                    "git": {
                        "uri": "https://github.com/landocalrizzian/jupyter-notebooks",
                        "ref": "summit-notebook"
                    },
                    "contextDir": "summit-notebook-mmgaggle"
                },
                "strategy": {
                    "type": "Source",
                    "sourceStrategy": {
                        "from": {
                            "kind": "ImageStreamTag",
                            "name": "mmgaggle-openshift-spark-py36:latest"
                        }
                    }
                },
                "output": {
                    "to": {
                        "kind": "ImageStreamTag",
                        "name": "s2i-mmgaggle-minimal-notebook:3.6"
                    }
                },
                "resources": {
                    "limits": {
                        "memory": "2Gi"
                    }
                }
            }
        }
    ]
}
